{"skeleton":{"hash":"dS4jf0GaJBKSh2mm9UAKfZcOuts","spine":"3.8.99","images":"./images/","audio":""},"bones":[{"name":"root"},{"name":"all","parent":"root"},{"name":"wx","parent":"all"},{"name":"wx_word","parent":"wx","y":-41},{"name":"wx_char","parent":"wx","x":27.8,"y":-49.65},{"name":"wx_gun","parent":"wx_char","length":30.75,"rotation":121.21,"x":-48.54,"y":7.88},{"name":"wx_head","parent":"wx_char","length":14.32,"rotation":103.8,"x":3.68,"y":15.97},{"name":"wx_hat","parent":"wx_head","rotation":-103.8,"x":73.98,"y":11.92},{"name":"wx_hair1-1","parent":"wx_head","length":32.35,"rotation":-164.2,"x":63.44,"y":-16.98},{"name":"wx_hair1-2","parent":"wx_hair1-1","length":26.97,"rotation":-2.82,"x":32.35},{"name":"wx_hair1-3","parent":"wx_hair1-2","length":30.22,"rotation":-3.08,"x":26.97},{"name":"wx_hair2-1","parent":"wx_head","length":51.04,"rotation":-169.04,"x":67.11,"y":-5.15},{"name":"wx_hair2-2","parent":"wx_hair2-1","length":62.62,"rotation":-0.13,"x":51.04},{"name":"wx_hair3-1","parent":"wx_head","length":34.45,"rotation":146.35,"x":64.28,"y":24.56},{"name":"wx_hair3-2","parent":"wx_hair3-1","length":71.03,"rotation":11.11,"x":34.45},{"name":"wx_spark","parent":"wx_gun","rotation":-89.56,"x":139.12,"y":-2.21,"scaleX":0.6748,"scaleY":0.8638,"color":"000000ff"},{"name":"wx_ani","parent":"wx_char","x":-27.8,"y":49.65,"scaleX":1.1,"scaleY":1.1,"color":"000000ff"},{"name":"wx_back","parent":"wx","color":"000000ff"}],"slots":[{"name":"wx_back","bone":"wx_back","color":"ffc55eff","blend":"additive"},{"name":"wx_frame2","bone":"wx"},{"name":"wx_mask","bone":"wx"},{"name":"wx_hat2","bone":"wx_hat"},{"name":"wx_hair3","bone":"wx_hair3-1"},{"name":"wx_hair2","bone":"wx_hair2-1"},{"name":"wx_cloth","bone":"wx_char"},{"name":"wx_face","bone":"wx_head"},{"name":"wx_hair1","bone":"wx_hair1-1"},{"name":"wx_hat1","bone":"wx_hat"},{"name":"wx_gun","bone":"wx_gun"},{"name":"wx_frame1","bone":"wx"},{"name":"wx_US","bone":"wx_word"},{"name":"wx_VN","bone":"wx_word"},{"name":"wx_TH","bone":"wx_word"},{"name":"wx_BR","bone":"wx_word"},{"name":"wx_ms-MY","bone":"wx_word"},{"name":"wx_LO","bone":"wx_word"},{"name":"wx_KR","bone":"wx_word"},{"name":"wx_JP","bone":"wx_word"},{"name":"wx_ID","bone":"wx_word"},{"name":"wx_PH","bone":"wx_word"},{"name":"wx_ES","bone":"wx_word"},{"name":"wx_MY","bone":"wx_word"},{"name":"wx_TW","bone":"wx_word"},{"name":"wx_CN","bone":"wx_word"},{"name":"wx_US_add","bone":"wx_word","blend":"additive"},{"name":"wx_VN_add","bone":"wx_word","blend":"additive"},{"name":"wx_TH_add","bone":"wx_word","blend":"additive"},{"name":"wx_BR_add","bone":"wx_word","blend":"additive"},{"name":"wx_ms-MY_add","bone":"wx_word","blend":"additive"},{"name":"wx_LO_add","bone":"wx_word","blend":"additive"},{"name":"wx_KR_add","bone":"wx_word","blend":"additive"},{"name":"wx_JP_add","bone":"wx_word","blend":"additive"},{"name":"wx_ID_add","bone":"wx_word","blend":"additive"},{"name":"wx_PH_add","bone":"wx_word","blend":"additive"},{"name":"wx_ES_add","bone":"wx_word","blend":"additive"},{"name":"wx_MY_add","bone":"wx_word","blend":"additive"},{"name":"wx_TW_add","bone":"wx_word","blend":"additive"},{"name":"wx_CN_add","bone":"wx_word","blend":"additive"},{"name":"wx_spark","bone":"wx_spark","blend":"additive"},{"name":"wx_ani","bone":"wx_ani","blend":"additive"}],"skins":[{"name":"default","attachments":{"wx_ani":{"wx_ani/wx_ani_05":{"width":200,"height":200},"wx_ani/wx_ani_06":{"width":200,"height":200},"wx_ani/wx_ani_07":{"width":200,"height":200},"wx_ani/wx_ani_08":{"width":200,"height":200},"wx_ani/wx_ani_09":{"width":200,"height":200},"wx_ani/wx_ani_10":{"width":200,"height":200},"wx_ani/wx_ani_11":{"width":200,"height":200},"wx_ani/wx_ani_12":{"width":200,"height":200},"wx_ani/wx_ani_13":{"width":200,"height":200},"wx_ani/wx_ani_14":{"width":200,"height":200},"wx_ani/wx_ani_15":{"width":200,"height":200},"wx_ani/wx_ani_16":{"width":200,"height":200},"wx_ani/wx_ani_17":{"width":200,"height":200},"wx_ani/wx_ani_18":{"width":200,"height":200},"wx_ani/wx_ani_19":{"width":200,"height":200},"wx_ani/wx_ani_20":{"width":200,"height":200},"wx_ani/wx_ani_21":{"width":200,"height":200},"wx_ani/wx_ani_22":{"width":200,"height":200}},"wx_back":{"wx_back/wx_back_00":{"width":250,"height":250},"wx_back/wx_back_01":{"width":250,"height":250},"wx_back/wx_back_02":{"width":250,"height":250},"wx_back/wx_back_03":{"width":250,"height":250},"wx_back/wx_back_04":{"width":250,"height":250},"wx_back/wx_back_05":{"width":250,"height":250},"wx_back/wx_back_06":{"width":250,"height":250},"wx_back/wx_back_07":{"width":250,"height":250},"wx_back/wx_back_08":{"width":250,"height":250},"wx_back/wx_back_09":{"width":250,"height":250},"wx_back/wx_back_10":{"width":250,"height":250},"wx_back/wx_back_11":{"width":250,"height":250},"wx_back/wx_back_12":{"width":250,"height":250},"wx_back/wx_back_13":{"width":250,"height":250},"wx_back/wx_back_14":{"width":250,"height":250},"wx_back/wx_back_15":{"width":250,"height":250},"wx_back/wx_back_16":{"width":250,"height":250},"wx_back/wx_back_17":{"width":250,"height":250},"wx_back/wx_back_18":{"width":250,"height":250},"wx_back/wx_back_19":{"width":250,"height":250},"wx_back/wx_back_20":{"width":250,"height":250},"wx_back/wx_back_21":{"width":250,"height":250},"wx_back/wx_back_22":{"width":250,"height":250},"wx_back/wx_back_23":{"width":250,"height":250},"wx_back/wx_back_24":{"width":250,"height":250},"wx_back/wx_back_25":{"width":250,"height":250},"wx_back/wx_back_26":{"width":250,"height":250},"wx_back/wx_back_27":{"width":250,"height":250},"wx_back/wx_back_28":{"width":250,"height":250},"wx_back/wx_back_29":{"width":250,"height":250}},"wx_cloth":{"wx_cloth":{"x":-12.3,"y":-9.35,"width":185,"height":150}},"wx_face":{"wx_face":{"type":"mesh","hull":4,"width":75,"height":82,"uvs":[1,1,0,1,0,0,1,0,0.06531,0.48242,0.09171,0.47729,0.10771,0.44729,0.15091,0.43778,0.19251,0.43632,0.21731,0.45534,0.23251,0.46924,0.20771,0.49412,0.16451,0.51168,0.12611,0.50803,0.42677,0.43313,0.44202,0.39879,0.48015,0.37786,0.53237,0.37679,0.57813,0.38269,0.61098,0.38537,0.57285,0.40683,0.53882,0.43635,0.49482,0.44815,0.4561,0.4444,0.28121,0.79695,0.34777,0.80266,0.41225,0.78934,0.48713,0.77222,0.54537,0.74369,0.58489,0.69803,0.23961,0.77603,0.30604,0.75946,0.34924,0.75556,0.37964,0.74044,0.42817,0.74337,0.49004,0.74532,0.5119,0.78239,0.47617,0.82044,0.4159,0.84532,0.36684,0.85117,0.32524,0.83361,0.30017,0.81117],"triangles":[17,2,3,16,2,17,18,17,3,19,18,3,15,2,16,20,17,18,20,18,19,15,8,2,15,9,8,21,17,20,7,2,8,23,15,16,14,15,23,6,2,7,21,22,16,21,16,17,23,16,22,14,9,15,10,9,14,6,4,2,5,4,6,11,8,9,11,9,10,13,6,7,5,6,13,11,12,7,11,7,8,13,7,12,29,20,19,21,20,29,22,21,29,33,10,14,33,14,23,11,10,33,23,34,33,22,34,23,22,29,34,29,35,34,28,35,29,33,31,11,32,31,33,12,11,31,27,34,35,27,35,28,30,12,31,36,27,28,26,33,34,26,34,27,24,30,31,25,31,32,24,31,25,32,33,26,25,32,26,41,24,25,37,26,27,37,27,36,40,41,25,38,26,37,39,25,26,39,40,25,26,38,39,4,1,2,4,5,13,30,1,4,19,3,0,29,19,0,28,29,0,36,28,0,37,36,0,38,37,0,1,39,38,1,30,24,24,41,1,13,12,30,30,4,13,40,1,41,1,40,39,0,1,38],"vertices":[-8.16,-10.89,9.73,61.94,89.36,42.38,71.47,-30.45,49.78,47.06,49.71,45.04,51.81,43.29,51.8,39.96,51.17,36.9,49.21,35.46,47.83,34.63,46.3,36.92,45.67,40.41,46.65,43.14,47.24,19.77,49.7,17.99,50.68,14.8,49.83,10.98,48.54,7.76,47.74,5.42,46.72,8.62,44.97,11.67,44.82,15.11,45.81,17.86,20.87,37.49,19.22,32.75,19.13,27.8,19.15,22.01,20.38,17.21,23.31,13.44,23.28,40.11,23.41,34.95,22.95,31.73,23.61,29.22,22.5,25.74,21.24,21.27,17.9,20.4,15.51,23.75,14.61,28.63,15.02,32.31,17.16,35,19.4,36.39],"edges":[0,2,2,4,4,6,0,6,8,10,10,12,12,14,14,16,16,18,18,20,20,22,22,24,24,26,26,10,28,30,30,32,32,34,34,36,36,38,38,40,40,42,42,44,44,46,46,28,48,50,50,52,52,54,54,56,56,58,48,60,48,62,62,64,64,66,66,68,68,70,70,56,56,72,72,74,74,76,76,78,78,80,80,82,82,48]}},"wx_frame1":{"wx_frame1":{"y":-49.5,"width":122,"height":25}},"wx_frame2":{"wx_frame2":{"x":0.5,"width":153,"height":182}},"wx_gun":{"wx_gun":{"x":7.89,"y":15.4,"rotation":-121.21,"width":54,"height":150}},"wx_hair1":{"wx_hair1":{"type":"mesh","hull":17,"width":71,"height":81,"uvs":[0.2223,0,0,0.06026,0,0.16041,0.18275,0.22589,0.28382,0.36841,0.26624,0.58411,0.41125,0.717,0.76061,0.81715,0.6881,1,0.94077,1,1,0.93848,1,0.77093,0.90342,0.55715,0.81114,0.40308,0.76061,0.16426,0.53649,0.0853,0.42444,0],"triangles":[7,6,12,7,12,11,7,11,10,9,8,7,10,9,7,4,13,6,6,13,12,5,4,6,3,2,1,0,3,1,16,3,0,15,3,16,15,4,3,15,13,4,14,13,15],"vertices":[1,8,-0.53,-0.91,1,1,8,-4.08,-17.04,1,1,8,2.97,-21.05,1,1,8,13.99,-12.39,1,2,8,27.57,-11.85,0.71681,9,-4.19,-12.07,0.28319,3,8,42.15,-21.56,0.05574,9,10.85,-21.05,0.91537,10,-14.96,-21.89,0.02889,2,9,25.1,-16.71,0.70524,10,-0.97,-16.79,0.29476,1,10,16.43,2.66,1,1,10,27.92,-8.01,1,1,10,35.13,8.42,1,1,10,32.26,14.27,1,2,9,47.83,18.64,0.00216,10,19.83,19.73,0.99784,3,8,62.59,18.85,0.00539,9,29.28,20.32,0.31816,10,1.22,20.41,0.67644,3,8,48.5,19.32,0.14658,9,15.19,20.09,0.70822,10,-12.84,19.43,0.1452,3,8,29.91,25.75,0.69758,9,-3.7,25.6,0.30236,10,-31.99,23.92,0.00006,2,8,16.49,15.08,0.98081,9,-16.58,14.28,0.01919,1,8,6.55,11.57,1],"edges":[0,2,2,4,4,6,6,8,8,10,10,12,12,14,14,16,16,18,18,20,20,22,22,24,24,26,26,28,28,30,30,32,0,32]}},"wx_hair2":{"wx_hair2":{"type":"mesh","hull":20,"width":113,"height":130,"uvs":[0.20277,0,0.01597,0,0.03261,0.15087,0.06961,0.24893,0,0.30842,0,0.49009,0.04556,0.58173,0.15284,0.64121,0.28415,0.76179,0.4035,0.86964,0.57181,1,0.78081,1,1,0.92913,1,0.68637,0.93617,0.59151,0.79746,0.46129,0.72348,0.27641,0.62175,0.1285,0.44974,0.01596,0.35172,0],"triangles":[12,11,13,13,11,10,13,10,14,10,9,14,9,15,14,9,8,15,8,7,15,15,7,16,7,6,5,16,7,17,17,19,18,19,17,7,0,19,3,7,5,3,19,7,3,5,4,3,3,2,0,2,1,0],"vertices":[1,11,-11.06,-5.81,1,1,11,-19.5,-25.15,1,2,11,-0.77,-31.27,0.97638,12,-51.74,-31.38,0.02362,2,11,12.59,-32.53,0.88421,12,-38.38,-32.62,0.11579,2,11,16.54,-42.83,0.77422,12,-34.41,-42.91,0.22578,2,11,38.18,-52.27,0.53903,12,-12.74,-52.3,0.46097,2,11,51.16,-52.31,0.41696,12,0.24,-52.31,0.58304,2,11,63.1,-44.29,0.24901,12,12.15,-44.27,0.75099,2,11,83.39,-36.96,0.03559,12,32.44,-36.88,0.96441,2,11,101.64,-30.2,0.00015,12,50.66,-30.09,0.99985,1,12,73.77,-19.37,1,1,12,83.17,2.3,1,1,12,84.56,28.69,1,1,12,55.61,41.23,1,2,11,92.55,39.43,0.00051,12,41.42,39.52,0.99949,2,11,70.77,31.83,0.10456,12,19.66,31.87,0.89544,2,11,45.4,33.77,0.70909,12,-5.72,33.76,0.29091,2,11,23.18,30.92,0.98603,12,-27.93,30.86,0.01397,1,11,2,18.95,1,1,11,-4.33,9.62,1],"edges":[0,2,2,4,4,6,6,8,8,10,10,12,12,14,14,16,16,18,18,20,20,22,22,24,24,26,26,28,28,30,30,32,32,34,34,36,36,38,0,38]}},"wx_hair3":{"wx_hair3":{"type":"mesh","hull":20,"width":135,"height":138,"uvs":[0.14381,0.04382,0.03881,0.1616,0,0.25747,0,0.39717,0.02901,0.48345,0,0.51221,0,0.64917,0,0.78338,0.05281,0.8546,0.09481,0.94499,0.25161,0.97649,0.4266,0.98608,0.6002,0.97375,0.6548,0.84364,0.6534,0.60123,0.5288,0.3506,0.4868,0.16982,0.4518,0.04656,0.4154,0,0.25021,0],"triangles":[12,11,13,14,13,11,11,10,14,14,10,8,4,15,14,9,8,10,6,14,8,4,14,6,8,7,6,6,5,4,17,4,3,15,4,16,16,4,17,0,17,1,0,19,17,19,18,17,17,2,1,17,3,2],"vertices":[1,13,-6.37,-14.92,1,1,13,13.73,-22.74,1,2,13,27.96,-23.17,0.93748,14,-10.83,-21.49,0.06252,2,13,46.09,-16.62,0.31168,14,8.22,-18.55,0.68832,2,13,55.96,-8.89,0.01426,14,19.39,-12.87,0.98574,2,13,61.02,-11.23,0.00029,14,23.91,-16.14,0.99971,1,14,42.59,-13.27,1,1,14,60.9,-10.45,1,1,14,69.53,-1.91,1,1,14,81,5.59,1,2,13,109.75,42.48,0.00621,14,82.07,27.17,0.99379,2,13,102.97,65.15,0.03078,14,79.79,50.73,0.96922,2,13,93.41,86.61,0.05444,14,74.54,73.63,0.94556,2,13,74.02,87.45,0.08667,14,55.68,78.19,0.91333,2,13,42.62,75.91,0.24402,14,22.64,72.91,0.75598,2,13,15.8,48.34,0.68615,14,-8.99,51.03,0.31385,2,13,-5.74,34.53,0.96519,14,-32.78,41.63,0.03481,2,13,-20.13,24.31,0.99962,14,-48.87,34.37,0.00038,1,13,-24.51,17.51,1,1,13,-16.93,-3.47,1],"edges":[0,2,2,4,4,6,6,8,8,10,10,12,12,14,14,16,16,18,18,20,20,22,22,24,24,26,26,28,28,30,30,32,32,34,34,36,36,38,0,38]}},"wx_hat1":{"wx_hat1":{"x":-5.25,"y":4.18,"width":124,"height":65}},"wx_hat2":{"wx_hat2":{"x":47.25,"y":0.18,"width":29,"height":35}},"wx_mask":{"wx_mask":{"type":"clipping","end":"wx_gun","vertexCount":6,"color":"ce3a3aff","vertices":[60.75,101.8,60.96,149.16,-150.49,150.11,-149.93,-38.11,-65.37,-38.08,60.13,-38.04]}},"wx_spark":{"spark/spark_00":{"width":200,"height":200},"spark/spark_01":{"width":200,"height":200},"spark/spark_02":{"width":200,"height":200},"spark/spark_03":{"width":200,"height":200},"spark/spark_04":{"width":200,"height":200},"spark/spark_05":{"width":200,"height":200},"spark/spark_06":{"width":200,"height":200},"spark/spark_07":{"width":200,"height":200},"spark/spark_08":{"width":200,"height":200},"spark/spark_09":{"width":200,"height":200}}}},{"name":"en-MY","attachments":{"wx_MY":{"en-MY":{"name":"wx_EN","y":-0.5,"width":124,"height":39}},"wx_MY_add":{"en-MY":{"name":"wx_EN","y":-0.5,"width":124,"height":39}}}},{"name":"en-US","attachments":{"wx_US":{"en-US":{"name":"wx_EN","y":-0.5,"width":124,"height":39}},"wx_US_add":{"en-US":{"name":"wx_EN","y":-0.5,"width":124,"height":39}}}},{"name":"es-ES","attachments":{"wx_ES":{"es-ES":{"name":"wx_EN","y":-0.5,"width":124,"height":39}},"wx_ES_add":{"es-ES":{"name":"wx_EN","y":-0.5,"width":124,"height":39}}}},{"name":"fil-PH","attachments":{"wx_PH":{"fil-PH":{"name":"wx_EN","y":-0.5,"width":124,"height":39}},"wx_PH_add":{"fil-PH":{"name":"wx_EN","y":-0.5,"width":124,"height":39}}}},{"name":"id-ID","attachments":{"wx_ID":{"id-ID":{"name":"wx_EN","y":-0.5,"width":124,"height":39}},"wx_ID_add":{"id-ID":{"name":"wx_EN","y":-0.5,"width":124,"height":39}}}},{"name":"ja-JP","attachments":{"wx_JP":{"ja-JP":{"name":"wx_EN","y":-0.5,"width":124,"height":39}},"wx_JP_add":{"ja-JP":{"name":"wx_EN","y":-0.5,"width":124,"height":39}}}},{"name":"ko-KR","attachments":{"wx_KR":{"ko-KR":{"name":"wx_EN","y":-0.5,"width":124,"height":39}},"wx_KR_add":{"ko-KR":{"name":"wx_EN","y":-0.5,"width":124,"height":39}}}},{"name":"lo-LO","attachments":{"wx_LO":{"lo-LO":{"name":"wx_EN","y":-0.5,"width":124,"height":39}},"wx_LO_add":{"lo-LO":{"name":"wx_EN","y":-0.5,"width":124,"height":39}}}},{"name":"ms-MY","attachments":{"wx_ms-MY":{"ms-MY":{"name":"wx_EN","y":-0.5,"width":124,"height":39}},"wx_ms-MY_add":{"ms-MY":{"name":"wx_EN","y":-0.5,"width":124,"height":39}}}},{"name":"pt-BR","attachments":{"wx_BR":{"pt-BR":{"name":"wx_EN","y":-0.5,"width":124,"height":39}},"wx_BR_add":{"pt-BR":{"name":"wx_EN","y":-0.5,"width":124,"height":39}}}},{"name":"th-TH","attachments":{"wx_TH":{"th-TH":{"name":"wx_EN","y":-0.5,"width":124,"height":39}},"wx_TH_add":{"th-TH":{"name":"wx_EN","y":-0.5,"width":124,"height":39}}}},{"name":"vi-VN","attachments":{"wx_VN":{"vi-VN":{"name":"wx_EN","y":-0.5,"width":124,"height":39}},"wx_VN_add":{"vi-VN":{"name":"wx_EN","y":-0.5,"width":124,"height":39}}}},{"name":"zh-CN","attachments":{"wx_CN":{"zh-CN":{"name":"wx_TW","y":0.5,"width":86,"height":41}},"wx_CN_add":{"zh-CN":{"name":"wx_TW","y":0.5,"width":86,"height":41}}}},{"name":"zh-TW","attachments":{"wx_TW":{"wx_TW":{"y":0.5,"width":86,"height":41}},"wx_TW_add":{"wx_TW":{"y":0.5,"width":86,"height":41}}}}],"animations":{"play":{"slots":{"wx_BR":{"color":[{"color":"ffffff00","curve":0.25,"c3":0.75},{"time":0.1,"color":"ffffffff"}],"attachment":[{"name":"pt-BR"}]},"wx_BR_add":{"color":[{"color":"ffffff00","curve":0.25,"c3":0.75},{"time":0.1667,"color":"ffffffff","curve":0.25,"c3":0.75},{"time":0.3333,"color":"ffffff00"}],"attachment":[{"name":"pt-BR"}]},"wx_CN":{"color":[{"color":"ffffff00","curve":0.25,"c3":0.75},{"time":0.1,"color":"ffffffff"}],"attachment":[{"name":"zh-CN"}]},"wx_CN_add":{"color":[{"color":"ffffff00","curve":0.25,"c3":0.75},{"time":0.1667,"color":"ffffffff","curve":0.25,"c3":0.75},{"time":0.3333,"color":"ffffff00"}],"attachment":[{"name":"zh-CN"}]},"wx_ES":{"color":[{"color":"ffffff00","curve":0.25,"c3":0.75},{"time":0.1,"color":"ffffffff"}],"attachment":[{"name":"es-ES"}]},"wx_ES_add":{"color":[{"color":"ffffff00","curve":0.25,"c3":0.75},{"time":0.1667,"color":"ffffffff","curve":0.25,"c3":0.75},{"time":0.3333,"color":"ffffff00"}],"attachment":[{"name":"es-ES"}]},"wx_ID":{"color":[{"color":"ffffff00","curve":0.25,"c3":0.75},{"time":0.1,"color":"ffffffff"}],"attachment":[{"name":"id-ID"}]},"wx_ID_add":{"color":[{"color":"ffffff00","curve":0.25,"c3":0.75},{"time":0.1667,"color":"ffffffff","curve":0.25,"c3":0.75},{"time":0.3333,"color":"ffffff00"}],"attachment":[{"name":"id-ID"}]},"wx_JP":{"color":[{"color":"ffffff00","curve":0.25,"c3":0.75},{"time":0.1,"color":"ffffffff"}],"attachment":[{"name":"ja-JP"}]},"wx_JP_add":{"color":[{"color":"ffffff00","curve":0.25,"c3":0.75},{"time":0.1667,"color":"ffffffff","curve":0.25,"c3":0.75},{"time":0.3333,"color":"ffffff00"}],"attachment":[{"name":"ja-JP"}]},"wx_KR":{"color":[{"color":"ffffff00","curve":0.25,"c3":0.75},{"time":0.1,"color":"ffffffff"}],"attachment":[{"name":"ko-KR"}]},"wx_KR_add":{"color":[{"color":"ffffff00","curve":0.25,"c3":0.75},{"time":0.1667,"color":"ffffffff","curve":0.25,"c3":0.75},{"time":0.3333,"color":"ffffff00"}],"attachment":[{"name":"ko-KR"}]},"wx_LO":{"color":[{"color":"ffffff00","curve":0.25,"c3":0.75},{"time":0.1,"color":"ffffffff"}],"attachment":[{"name":"lo-LO"}]},"wx_LO_add":{"color":[{"color":"ffffff00","curve":0.25,"c3":0.75},{"time":0.1667,"color":"ffffffff","curve":0.25,"c3":0.75},{"time":0.3333,"color":"ffffff00"}],"attachment":[{"name":"lo-LO"}]},"wx_MY":{"color":[{"color":"ffffff00","curve":0.25,"c3":0.75},{"time":0.1,"color":"ffffffff"}],"attachment":[{"name":"en-MY"}]},"wx_MY_add":{"color":[{"color":"ffffff00","curve":0.25,"c3":0.75},{"time":0.1667,"color":"ffffffff","curve":0.25,"c3":0.75},{"time":0.3333,"color":"ffffff00"}],"attachment":[{"name":"en-MY"}]},"wx_PH":{"color":[{"color":"ffffff00","curve":0.25,"c3":0.75},{"time":0.1,"color":"ffffffff"}],"attachment":[{"name":"fil-PH"}]},"wx_PH_add":{"color":[{"color":"ffffff00","curve":0.25,"c3":0.75},{"time":0.1667,"color":"ffffffff","curve":0.25,"c3":0.75},{"time":0.3333,"color":"ffffff00"}],"attachment":[{"name":"fil-PH"}]},"wx_TH":{"color":[{"color":"ffffff00","curve":0.25,"c3":0.75},{"time":0.1,"color":"ffffffff"}],"attachment":[{"name":"th-TH"}]},"wx_TH_add":{"color":[{"color":"ffffff00","curve":0.25,"c3":0.75},{"time":0.1667,"color":"ffffffff","curve":0.25,"c3":0.75},{"time":0.3333,"color":"ffffff00"}],"attachment":[{"name":"th-TH"}]},"wx_TW":{"color":[{"color":"ffffff00","curve":0.25,"c3":0.75},{"time":0.1,"color":"ffffffff"}],"attachment":[{"name":"wx_TW"}]},"wx_TW_add":{"color":[{"color":"ffffff00","curve":0.25,"c3":0.75},{"time":0.1667,"color":"ffffffff","curve":0.25,"c3":0.75},{"time":0.3333,"color":"ffffff00"}],"attachment":[{"name":"wx_TW"}]},"wx_US":{"color":[{"color":"ffffff00","curve":0.25,"c3":0.75},{"time":0.1,"color":"ffffffff"}],"attachment":[{"name":"en-US"}]},"wx_US_add":{"color":[{"color":"ffffff00","curve":0.25,"c3":0.75},{"time":0.1667,"color":"ffffffff","curve":0.25,"c3":0.75},{"time":0.3333,"color":"ffffff00"}],"attachment":[{"name":"en-US"}]},"wx_VN":{"color":[{"color":"ffffff00","curve":0.25,"c3":0.75},{"time":0.1,"color":"ffffffff"}],"attachment":[{"name":"vi-VN"}]},"wx_VN_add":{"color":[{"color":"ffffff00","curve":0.25,"c3":0.75},{"time":0.1667,"color":"ffffffff","curve":0.25,"c3":0.75},{"time":0.3333,"color":"ffffff00"}],"attachment":[{"name":"vi-VN"}]},"wx_back":{"attachment":[{"time":0.1667,"name":"wx_back/wx_back_00"}]},"wx_cloth":{"color":[{"color":"ffffff00","curve":0.25,"c3":0.75},{"time":0.1,"color":"ffffffff"}],"attachment":[{"name":"wx_cloth"}]},"wx_face":{"color":[{"color":"ffffff00","curve":0.25,"c3":0.75},{"time":0.1,"color":"ffffffff"}],"attachment":[{"name":"wx_face"}]},"wx_frame1":{"color":[{"color":"ffffff00","curve":0.25,"c3":0.75},{"time":0.1,"color":"ffffffff"}],"attachment":[{"name":"wx_frame1"}]},"wx_frame2":{"color":[{"color":"ffffff00","curve":0.25,"c3":0.75},{"time":0.1,"color":"ffffffff"}],"attachment":[{"name":"wx_frame2"}]},"wx_gun":{"color":[{"color":"ffffff00","curve":0.25,"c3":0.75},{"time":0.1,"color":"ffffffff"}],"attachment":[{"name":"wx_gun"}]},"wx_hair1":{"color":[{"color":"ffffff00","curve":0.25,"c3":0.75},{"time":0.1,"color":"ffffffff"}],"attachment":[{"name":"wx_hair1"}]},"wx_hair2":{"color":[{"color":"ffffff00","curve":0.25,"c3":0.75},{"time":0.1,"color":"ffffffff"}],"attachment":[{"name":"wx_hair2"}]},"wx_hair3":{"color":[{"color":"ffffff00","curve":0.25,"c3":0.75},{"time":0.1,"color":"ffffffff"}],"attachment":[{"name":"wx_hair3"}]},"wx_hat1":{"color":[{"color":"ffffff00","curve":0.25,"c3":0.75},{"time":0.1,"color":"ffffffff"}],"attachment":[{"name":"wx_hat1"}]},"wx_hat2":{"color":[{"color":"ffffff00","curve":0.25,"c3":0.75},{"time":0.1,"color":"ffffffff"}],"attachment":[{"name":"wx_hat2"}]},"wx_mask":{"attachment":[{"name":"wx_mask"}]},"wx_ms-MY":{"color":[{"color":"ffffff00","curve":0.25,"c3":0.75},{"time":0.1,"color":"ffffffff"}],"attachment":[{"name":"ms-MY"}]},"wx_ms-MY_add":{"color":[{"color":"ffffff00","curve":0.25,"c3":0.75},{"time":0.1667,"color":"ffffffff","curve":0.25,"c3":0.75},{"time":0.3333,"color":"ffffff00"}],"attachment":[{"name":"ms-MY"}]}},"bones":{"wx":{"scale":[{"x":0.5,"y":0.5,"curve":0.25,"c3":0.75},{"time":0.1,"x":1.1,"y":1.1,"curve":0.25,"c3":0.75},{"time":0.2333}]},"wx_word":{"scale":[{"x":0.5,"y":0.5,"curve":0.25,"c3":0.75},{"time":0.1667,"x":1.2,"y":1.2,"curve":0.25,"c3":0.75},{"time":0.3333}]},"wx_gun":{"rotate":[{"curve":0.25,"c3":0.75},{"time":0.2,"angle":-3.53,"curve":0.25,"c3":0.75},{"time":0.4}],"translate":[{"curve":0.25,"c3":0.75},{"time":0.2,"y":5.94,"curve":0.25,"c3":0.75},{"time":0.4}]},"wx_head":{"translate":[{"curve":0.25,"c3":0.75},{"time":0.1333,"y":5.94,"curve":0.25,"c3":0.75},{"time":0.4}]},"wx_char":{"translate":[{"curve":0,"c2":0.06,"c3":0.336,"c4":0.61},{"time":0.2333,"x":-6.28,"y":7.18}],"scale":[{"curve":0,"c2":0.06,"c3":0.336,"c4":0.61},{"time":0.2333,"x":1.15,"y":1.15}]}},"deform":{"default":{"wx_mask":{"wx_mask":[{"offset":1,"vertices":[-74.98387,10.00999,0,0,0,78.76077,-16.5099,6.13199]}]}}}},"play_end":{"slots":{"wx_BR":{"attachment":[{"name":"pt-BR"}]},"wx_BR_add":{"color":[{"color":"ffffff00","curve":0.25,"c3":0.75},{"time":0.5,"color":"ffffff64","curve":0.25,"c3":0.75},{"time":1,"color":"ffffff00"}],"attachment":[{"name":"pt-BR"}]},"wx_CN":{"attachment":[{"name":"zh-CN"}]},"wx_CN_add":{"color":[{"color":"ffffff00","curve":0.25,"c3":0.75},{"time":0.5,"color":"ffffff64","curve":0.25,"c3":0.75},{"time":1,"color":"ffffff00"}],"attachment":[{"name":"zh-CN"}]},"wx_ES":{"attachment":[{"name":"es-ES"}]},"wx_ES_add":{"color":[{"color":"ffffff00","curve":0.25,"c3":0.75},{"time":0.5,"color":"ffffff64","curve":0.25,"c3":0.75},{"time":1,"color":"ffffff00"}],"attachment":[{"name":"es-ES"}]},"wx_ID":{"attachment":[{"name":"id-ID"}]},"wx_ID_add":{"color":[{"color":"ffffff00","curve":0.25,"c3":0.75},{"time":0.5,"color":"ffffff64","curve":0.25,"c3":0.75},{"time":1,"color":"ffffff00"}],"attachment":[{"name":"id-ID"}]},"wx_JP":{"attachment":[{"name":"ja-JP"}]},"wx_JP_add":{"color":[{"color":"ffffff00","curve":0.25,"c3":0.75},{"time":0.5,"color":"ffffff64","curve":0.25,"c3":0.75},{"time":1,"color":"ffffff00"}],"attachment":[{"name":"ja-JP"}]},"wx_KR":{"attachment":[{"name":"ko-KR"}]},"wx_KR_add":{"color":[{"color":"ffffff00","curve":0.25,"c3":0.75},{"time":0.5,"color":"ffffff64","curve":0.25,"c3":0.75},{"time":1,"color":"ffffff00"}],"attachment":[{"name":"ko-KR"}]},"wx_LO":{"attachment":[{"name":"lo-LO"}]},"wx_LO_add":{"color":[{"color":"ffffff00","curve":0.25,"c3":0.75},{"time":0.5,"color":"ffffff64","curve":0.25,"c3":0.75},{"time":1,"color":"ffffff00"}],"attachment":[{"name":"lo-LO"}]},"wx_MY":{"attachment":[{"name":"en-MY"}]},"wx_MY_add":{"color":[{"color":"ffffff00","curve":0.25,"c3":0.75},{"time":0.5,"color":"ffffff64","curve":0.25,"c3":0.75},{"time":1,"color":"ffffff00"}],"attachment":[{"name":"en-MY"}]},"wx_PH":{"attachment":[{"name":"fil-PH"}]},"wx_PH_add":{"color":[{"color":"ffffff00","curve":0.25,"c3":0.75},{"time":0.5,"color":"ffffff64","curve":0.25,"c3":0.75},{"time":1,"color":"ffffff00"}],"attachment":[{"name":"fil-PH"}]},"wx_TH":{"attachment":[{"name":"th-TH"}]},"wx_TH_add":{"color":[{"color":"ffffff00","curve":0.25,"c3":0.75},{"time":0.5,"color":"ffffff64","curve":0.25,"c3":0.75},{"time":1,"color":"ffffff00"}],"attachment":[{"name":"th-TH"}]},"wx_TW":{"attachment":[{"name":"wx_TW"}]},"wx_TW_add":{"color":[{"color":"ffffff00","curve":0.25,"c3":0.75},{"time":0.5,"color":"ffffff64","curve":0.25,"c3":0.75},{"time":1,"color":"ffffff00"}],"attachment":[{"name":"wx_TW"}]},"wx_US":{"attachment":[{"name":"en-US"}]},"wx_US_add":{"color":[{"color":"ffffff00","curve":0.25,"c3":0.75},{"time":0.5,"color":"ffffff64","curve":0.25,"c3":0.75},{"time":1,"color":"ffffff00"}],"attachment":[{"name":"en-US"}]},"wx_VN":{"attachment":[{"name":"vi-VN"}]},"wx_VN_add":{"color":[{"color":"ffffff00","curve":0.25,"c3":0.75},{"time":0.5,"color":"ffffff64","curve":0.25,"c3":0.75},{"time":1,"color":"ffffff00"}],"attachment":[{"name":"vi-VN"}]},"wx_back":{"color":[{"time":0.7667,"color":"ffc55eff","curve":0,"c2":0.06,"c3":0.336,"c4":0.61},{"time":1,"color":"ffc55d00"}],"attachment":[{"name":"wx_back/wx_back_00"},{"time":0.0333,"name":"wx_back/wx_back_01"},{"time":0.0667,"name":"wx_back/wx_back_02"},{"time":0.1,"name":"wx_back/wx_back_03"},{"time":0.1333,"name":"wx_back/wx_back_04"},{"time":0.1667,"name":"wx_back/wx_back_05"},{"time":0.2,"name":"wx_back/wx_back_06"},{"time":0.2333,"name":"wx_back/wx_back_07"},{"time":0.2667,"name":"wx_back/wx_back_08"},{"time":0.3,"name":"wx_back/wx_back_09"},{"time":0.3333,"name":"wx_back/wx_back_10"},{"time":0.3667,"name":"wx_back/wx_back_11"},{"time":0.4,"name":"wx_back/wx_back_12"},{"time":0.4333,"name":"wx_back/wx_back_13"},{"time":0.4667,"name":"wx_back/wx_back_14"},{"time":0.5,"name":"wx_back/wx_back_15"},{"time":0.5333,"name":"wx_back/wx_back_16"},{"time":0.5667,"name":"wx_back/wx_back_17"},{"time":0.6,"name":"wx_back/wx_back_18"},{"time":0.6333,"name":"wx_back/wx_back_19"},{"time":0.6667,"name":"wx_back/wx_back_20"},{"time":0.7,"name":"wx_back/wx_back_21"},{"time":0.7333,"name":"wx_back/wx_back_22"},{"time":0.7667,"name":"wx_back/wx_back_23"},{"time":0.8,"name":"wx_back/wx_back_24"},{"time":0.8333,"name":"wx_back/wx_back_25"},{"time":0.8667,"name":"wx_back/wx_back_26"},{"time":0.9,"name":"wx_back/wx_back_27"},{"time":0.9333,"name":"wx_back/wx_back_28"},{"time":0.9667,"name":"wx_back/wx_back_29"},{"time":1,"name":"wx_back/wx_back_00"}]},"wx_cloth":{"attachment":[{"name":"wx_cloth"}]},"wx_face":{"attachment":[{"name":"wx_face"}]},"wx_frame1":{"attachment":[{"name":"wx_frame1"}]},"wx_frame2":{"attachment":[{"name":"wx_frame2"}]},"wx_gun":{"attachment":[{"name":"wx_gun"}]},"wx_hair1":{"attachment":[{"name":"wx_hair1"}]},"wx_hair2":{"attachment":[{"name":"wx_hair2"}]},"wx_hair3":{"attachment":[{"name":"wx_hair3"}]},"wx_hat1":{"attachment":[{"name":"wx_hat1"}]},"wx_hat2":{"attachment":[{"name":"wx_hat2"}]},"wx_mask":{"attachment":[{"name":"wx_mask"}]},"wx_ms-MY":{"attachment":[{"name":"ms-MY"}]},"wx_ms-MY_add":{"color":[{"color":"ffffff00","curve":0.25,"c3":0.75},{"time":0.5,"color":"ffffff64","curve":0.25,"c3":0.75},{"time":1,"color":"ffffff00"}],"attachment":[{"name":"ms-MY"}]}},"bones":{"wx_gun":{"rotate":[{"curve":0.25,"c3":0.75},{"time":0.6,"angle":-4.91,"curve":0.25,"c3":0.75},{"time":1}]},"wx_hair1-1":{"rotate":[{"curve":0.25,"c3":0.75},{"time":0.3667,"angle":-2.26,"curve":0.25,"c3":0.75},{"time":1}]},"wx_hair2-1":{"rotate":[{"curve":0.25,"c3":0.75},{"time":0.5333,"angle":-1.95,"curve":0.25,"c3":0.75},{"time":1}]},"wx_hair3-1":{"rotate":[{"curve":0.25,"c3":0.75},{"time":0.4333,"angle":1.65,"curve":0.25,"c3":0.75},{"time":1}]},"wx_hair1-3":{"rotate":[{"curve":0.25,"c3":0.75},{"time":0.2667,"angle":-2.26,"curve":0.25,"c3":0.75},{"time":0.5}]},"wx_hair1-2":{"rotate":[{"curve":0.25,"c3":0.75},{"time":0.2333,"angle":-2.26,"curve":0.25,"c3":0.75},{"time":0.5}]},"wx_hair2-2":{"rotate":[{"curve":0.25,"c3":0.75},{"time":0.3,"angle":-1.95,"curve":0.25,"c3":0.75},{"time":0.5}]},"wx_hair3-2":{"rotate":[{"curve":0.25,"c3":0.75},{"time":0.2667,"angle":1.65,"curve":0.25,"c3":0.75},{"time":0.5}]},"wx_char":{"translate":[{"x":-6.28,"y":7.18,"curve":0.25,"c3":0.75},{"time":0.1667}],"scale":[{"x":1.15,"y":1.15,"curve":0.25,"c3":0.75},{"time":0.1667}]}},"deform":{"default":{"wx_face":{"wx_face":[{"curve":0.25,"c3":0.75},{"time":0.2333,"offset":12,"curve":"stepped","vertices":[-0.88809,0.06732,-0.88809,0.06732,-0.88809,0.06732,0,0,0,0,0.58624,-0.06862,1.24358,-0.15469,0.95919,-0.08484,0,0,-0.85317,0.20953,-0.67479,0.01496,-0.4615,-0.03743,0,0,0,0,0,0,0.88809,-0.06736,0.78206,-0.1921,0.42658,-0.10478]},{"time":0.8,"offset":12,"curve":0.25,"c3":0.75,"vertices":[-0.88809,0.06732,-0.88809,0.06732,-0.88809,0.06732,0,0,0,0,0.58624,-0.06862,1.24358,-0.15469,0.95919,-0.08484,0,0,-0.85317,0.20953,-0.67479,0.01496,-0.4615,-0.03743,0,0,0,0,0,0,0.88809,-0.06736,0.78206,-0.1921,0.42658,-0.10478]},{"time":1}]},"wx_mask":{"wx_mask":[{"curve":0,"c2":0.06,"c3":0.336,"c4":0.61,"vertices":[-0.49498,0,-0.49498,0,0,0,0,0,0,0,0.23401]},{"time":0.2,"vertices":[-0.804,-72.86391,79.21196,0,0,0,0,0,0,0,0.112]}]}}}},"play_loop":{"slots":{"wx_BR":{"attachment":[{"name":"pt-BR"}]},"wx_BR_add":{"color":[{"color":"ffffff00"},{"time":0.5,"color":"ffffff64"},{"time":1,"color":"ffffff00"}],"attachment":[{"name":"pt-BR"}]},"wx_CN":{"attachment":[{"name":"zh-CN"}]},"wx_CN_add":{"color":[{"color":"ffffff00"},{"time":0.5,"color":"ffffff64"},{"time":1,"color":"ffffff00"}],"attachment":[{"name":"zh-CN"}]},"wx_ES":{"attachment":[{"name":"es-ES"}]},"wx_ES_add":{"color":[{"color":"ffffff00"},{"time":0.5,"color":"ffffff64"},{"time":1,"color":"ffffff00"}],"attachment":[{"name":"es-ES"}]},"wx_ID":{"attachment":[{"name":"id-ID"}]},"wx_ID_add":{"color":[{"color":"ffffff00"},{"time":0.5,"color":"ffffff64"},{"time":1,"color":"ffffff00"}],"attachment":[{"name":"id-ID"}]},"wx_JP":{"attachment":[{"name":"ja-JP"}]},"wx_JP_add":{"color":[{"color":"ffffff00"},{"time":0.5,"color":"ffffff64"},{"time":1,"color":"ffffff00"}],"attachment":[{"name":"ja-JP"}]},"wx_KR":{"attachment":[{"name":"ko-KR"}]},"wx_KR_add":{"color":[{"color":"ffffff00"},{"time":0.5,"color":"ffffff64"},{"time":1,"color":"ffffff00"}],"attachment":[{"name":"ko-KR"}]},"wx_LO":{"attachment":[{"name":"lo-LO"}]},"wx_LO_add":{"color":[{"color":"ffffff00"},{"time":0.5,"color":"ffffff64"},{"time":1,"color":"ffffff00"}],"attachment":[{"name":"lo-LO"}]},"wx_MY":{"attachment":[{"name":"en-MY"}]},"wx_MY_add":{"color":[{"color":"ffffff00"},{"time":0.5,"color":"ffffff64"},{"time":1,"color":"ffffff00"}],"attachment":[{"name":"en-MY"}]},"wx_PH":{"attachment":[{"name":"fil-PH"}]},"wx_PH_add":{"color":[{"color":"ffffff00"},{"time":0.5,"color":"ffffff64"},{"time":1,"color":"ffffff00"}],"attachment":[{"name":"fil-PH"}]},"wx_TH":{"attachment":[{"name":"th-TH"}]},"wx_TH_add":{"color":[{"color":"ffffff00"},{"time":0.5,"color":"ffffff64"},{"time":1,"color":"ffffff00"}],"attachment":[{"name":"th-TH"}]},"wx_TW":{"attachment":[{"name":"wx_TW"}]},"wx_TW_add":{"color":[{"color":"ffffff00"},{"time":0.5,"color":"ffffff64"},{"time":1,"color":"ffffff00"}],"attachment":[{"name":"wx_TW"}]},"wx_US":{"attachment":[{"name":"en-US"}]},"wx_US_add":{"color":[{"color":"ffffff00"},{"time":0.5,"color":"ffffff64"},{"time":1,"color":"ffffff00"}],"attachment":[{"name":"en-US"}]},"wx_VN":{"attachment":[{"name":"vi-VN"}]},"wx_VN_add":{"color":[{"color":"ffffff00"},{"time":0.5,"color":"ffffff64"},{"time":1,"color":"ffffff00"}],"attachment":[{"name":"vi-VN"}]},"wx_back":{"attachment":[{"name":"wx_back/wx_back_00"},{"time":0.0333,"name":"wx_back/wx_back_01"},{"time":0.0667,"name":"wx_back/wx_back_02"},{"time":0.1,"name":"wx_back/wx_back_03"},{"time":0.1333,"name":"wx_back/wx_back_04"},{"time":0.1667,"name":"wx_back/wx_back_05"},{"time":0.2,"name":"wx_back/wx_back_06"},{"time":0.2333,"name":"wx_back/wx_back_07"},{"time":0.2667,"name":"wx_back/wx_back_08"},{"time":0.3,"name":"wx_back/wx_back_09"},{"time":0.3333,"name":"wx_back/wx_back_10"},{"time":0.3667,"name":"wx_back/wx_back_11"},{"time":0.4,"name":"wx_back/wx_back_12"},{"time":0.4333,"name":"wx_back/wx_back_13"},{"time":0.4667,"name":"wx_back/wx_back_14"},{"time":0.5,"name":"wx_back/wx_back_15"},{"time":0.5333,"name":"wx_back/wx_back_16"},{"time":0.5667,"name":"wx_back/wx_back_17"},{"time":0.6,"name":"wx_back/wx_back_18"},{"time":0.6333,"name":"wx_back/wx_back_19"},{"time":0.6667,"name":"wx_back/wx_back_20"},{"time":0.7,"name":"wx_back/wx_back_21"},{"time":0.7333,"name":"wx_back/wx_back_22"},{"time":0.7667,"name":"wx_back/wx_back_23"},{"time":0.8,"name":"wx_back/wx_back_24"},{"time":0.8333,"name":"wx_back/wx_back_25"},{"time":0.8667,"name":"wx_back/wx_back_26"},{"time":0.9,"name":"wx_back/wx_back_27"},{"time":0.9333,"name":"wx_back/wx_back_28"},{"time":0.9667,"name":"wx_back/wx_back_29"},{"time":1,"name":"wx_back/wx_back_00"}]},"wx_cloth":{"attachment":[{"name":"wx_cloth"}]},"wx_face":{"attachment":[{"name":"wx_face"}]},"wx_frame1":{"attachment":[{"name":"wx_frame1"}]},"wx_frame2":{"attachment":[{"name":"wx_frame2"}]},"wx_gun":{"attachment":[{"name":"wx_gun"}]},"wx_hair1":{"attachment":[{"name":"wx_hair1"}]},"wx_hair2":{"attachment":[{"name":"wx_hair2"}]},"wx_hair3":{"attachment":[{"name":"wx_hair3"}]},"wx_hat1":{"attachment":[{"name":"wx_hat1"}]},"wx_hat2":{"attachment":[{"name":"wx_hat2"}]},"wx_mask":{"attachment":[{"name":"wx_mask"}]},"wx_ms-MY":{"attachment":[{"name":"ms-MY"}]},"wx_ms-MY_add":{"color":[{"color":"ffffff00"},{"time":0.5,"color":"ffffff64"},{"time":1,"color":"ffffff00"}],"attachment":[{"name":"ms-MY"}]}},"bones":{"wx":{"scale":[{"curve":0.343,"c2":0.33,"c3":0.75},{"time":0.4,"x":1.1,"y":1.1,"curve":0.25,"c3":0.637,"c4":0.61},{"time":1}]},"wx_word":{"scale":[{"curve":0.343,"c2":0.33,"c3":0.75},{"time":0.5,"x":1.1,"y":1.1,"curve":0.25,"c3":0.637,"c4":0.61},{"time":1}]},"wx_gun":{"rotate":[{"curve":0.36,"c2":0.34,"c3":0.75},{"time":0.6,"angle":-4.91,"curve":0.25,"c3":0.709,"c4":0.68},{"time":1}]},"wx_hair1-1":{"rotate":[{"curve":0.334,"c2":0.34,"c3":0.75},{"time":0.3667,"angle":-2.26,"curve":0.25,"c3":0.683,"c4":0.67},{"time":1}]},"wx_hair2-1":{"rotate":[{"curve":0.334,"c2":0.34,"c3":0.75},{"time":0.5333,"angle":-1.95,"curve":0.25,"c3":0.683,"c4":0.67},{"time":1}]},"wx_hair3-1":{"rotate":[{"curve":0.334,"c2":0.34,"c3":0.75},{"time":0.4333,"angle":1.65,"curve":0.25,"c3":0.683,"c4":0.67},{"time":1}]},"wx_hair1-3":{"rotate":[{"curve":0.334,"c2":0.34,"c3":0.75},{"time":0.5,"angle":-2.26,"curve":0.25,"c3":0.683,"c4":0.67},{"time":1}]},"wx_hair1-2":{"rotate":[{"curve":0.334,"c2":0.34,"c3":0.75},{"time":0.4333,"angle":-2.26,"curve":0.25,"c3":0.683,"c4":0.67},{"time":1}]},"wx_hair2-2":{"rotate":[{"curve":0.334,"c2":0.34,"c3":0.75},{"time":0.6,"angle":-1.95,"curve":0.25,"c3":0.683,"c4":0.67},{"time":1}]},"wx_hair3-2":{"rotate":[{"curve":0.334,"c2":0.34,"c3":0.75},{"time":0.5,"angle":1.65,"curve":0.25,"c3":0.683,"c4":0.67},{"time":1}]},"wx_char":{"translate":[{"x":-6.28,"y":7.18}],"scale":[{"x":1.15,"y":1.15}]}},"deform":{"default":{"wx_face":{"wx_face":[{},{"time":0.2333,"offset":12,"curve":"stepped","vertices":[-0.88809,0.06732,-0.88809,0.06732,-0.88809,0.06732,0,0,0,0,0.58624,-0.06862,1.24358,-0.15469,0.95919,-0.08484,0,0,-0.85317,0.20953,-0.67479,0.01496,-0.4615,-0.03743,0,0,0,0,0,0,0.88809,-0.06736,0.78206,-0.1921,0.42658,-0.10478]},{"time":0.8,"offset":12,"vertices":[-0.88809,0.06732,-0.88809,0.06732,-0.88809,0.06732,0,0,0,0,0.58624,-0.06862,1.24358,-0.15469,0.95919,-0.08484,0,0,-0.85317,0.20953,-0.67479,0.01496,-0.4615,-0.03743,0,0,0,0,0,0,0.88809,-0.06736,0.78206,-0.1921,0.42658,-0.10478]},{"time":1}]},"wx_mask":{"wx_mask":[{"offset":1,"vertices":[-74.98387,10.00999,0,0,0,78.76077,-16.5099,6.13199]}]}}}},"play_win":{"slots":{"wx_BR":{"attachment":[{"name":"pt-BR"}]},"wx_BR_add":{"color":[{"color":"ffffff00","curve":0.25,"c3":0.75},{"time":0.8333,"color":"ffffffff"}],"attachment":[{"name":"pt-BR"}]},"wx_CN":{"attachment":[{"name":"zh-CN"}]},"wx_CN_add":{"color":[{"color":"ffffff00","curve":0.25,"c3":0.75},{"time":0.8333,"color":"ffffffff"}],"attachment":[{"name":"zh-CN"}]},"wx_ES":{"attachment":[{"name":"es-ES"}]},"wx_ES_add":{"color":[{"color":"ffffff00","curve":0.25,"c3":0.75},{"time":0.8333,"color":"ffffffff"}],"attachment":[{"name":"es-ES"}]},"wx_ID":{"attachment":[{"name":"id-ID"}]},"wx_ID_add":{"color":[{"color":"ffffff00","curve":0.25,"c3":0.75},{"time":0.8333,"color":"ffffffff"}],"attachment":[{"name":"id-ID"}]},"wx_JP":{"attachment":[{"name":"ja-JP"}]},"wx_JP_add":{"color":[{"color":"ffffff00","curve":0.25,"c3":0.75},{"time":0.8333,"color":"ffffffff"}],"attachment":[{"name":"ja-JP"}]},"wx_KR":{"attachment":[{"name":"ko-KR"}]},"wx_KR_add":{"color":[{"color":"ffffff00","curve":0.25,"c3":0.75},{"time":0.8333,"color":"ffffffff"}],"attachment":[{"name":"ko-KR"}]},"wx_LO":{"attachment":[{"name":"lo-LO"}]},"wx_LO_add":{"color":[{"color":"ffffff00","curve":0.25,"c3":0.75},{"time":0.8333,"color":"ffffffff"}],"attachment":[{"name":"lo-LO"}]},"wx_MY":{"attachment":[{"name":"en-MY"}]},"wx_MY_add":{"color":[{"color":"ffffff00","curve":0.25,"c3":0.75},{"time":0.8333,"color":"ffffffff"}],"attachment":[{"name":"en-MY"}]},"wx_PH":{"attachment":[{"name":"fil-PH"}]},"wx_PH_add":{"color":[{"color":"ffffff00","curve":0.25,"c3":0.75},{"time":0.8333,"color":"ffffffff"}],"attachment":[{"name":"fil-PH"}]},"wx_TH":{"attachment":[{"name":"th-TH"}]},"wx_TH_add":{"color":[{"color":"ffffff00","curve":0.25,"c3":0.75},{"time":0.8333,"color":"ffffffff"}],"attachment":[{"name":"th-TH"}]},"wx_TW":{"attachment":[{"name":"wx_TW"}]},"wx_TW_add":{"color":[{"color":"ffffff00","curve":0.25,"c3":0.75},{"time":0.8333,"color":"ffffffff"}],"attachment":[{"name":"wx_TW"}]},"wx_US":{"attachment":[{"name":"en-US"}]},"wx_US_add":{"color":[{"color":"ffffff00","curve":0.25,"c3":0.75},{"time":0.8333,"color":"ffffffff"}],"attachment":[{"name":"en-US"}]},"wx_VN":{"attachment":[{"name":"vi-VN"}]},"wx_VN_add":{"color":[{"color":"ffffff00","curve":0.25,"c3":0.75},{"time":0.8333,"color":"ffffffff"}],"attachment":[{"name":"vi-VN"}]},"wx_ani":{"color":[{"color":"ffffff95"}],"attachment":[{"time":0.1667,"name":"wx_ani/wx_ani_05"},{"time":0.2,"name":"wx_ani/wx_ani_06"},{"time":0.2333,"name":"wx_ani/wx_ani_07"},{"time":0.2667,"name":"wx_ani/wx_ani_08"},{"time":0.3,"name":"wx_ani/wx_ani_09"},{"time":0.3333,"name":"wx_ani/wx_ani_10"},{"time":0.3667,"name":"wx_ani/wx_ani_11"},{"time":0.4,"name":"wx_ani/wx_ani_12"},{"time":0.4333,"name":"wx_ani/wx_ani_13"},{"time":0.4667,"name":"wx_ani/wx_ani_14"},{"time":0.5,"name":"wx_ani/wx_ani_15"},{"time":0.5333,"name":"wx_ani/wx_ani_16"},{"time":0.5667,"name":"wx_ani/wx_ani_17"},{"time":0.6,"name":"wx_ani/wx_ani_18"},{"time":0.6333,"name":"wx_ani/wx_ani_19"},{"time":0.6667,"name":"wx_ani/wx_ani_20"},{"time":0.7,"name":"wx_ani/wx_ani_21"},{"time":0.7333,"name":"wx_ani/wx_ani_22"},{"time":0.7667,"name":null}]},"wx_back":{"attachment":[{"name":"wx_back/wx_back_00"},{"time":0.0333,"name":"wx_back/wx_back_01"},{"time":0.0667,"name":"wx_back/wx_back_02"},{"time":0.1,"name":"wx_back/wx_back_03"},{"time":0.1333,"name":"wx_back/wx_back_04"},{"time":0.1667,"name":"wx_back/wx_back_05"},{"time":0.2,"name":"wx_back/wx_back_06"},{"time":0.2333,"name":"wx_back/wx_back_07"},{"time":0.2667,"name":"wx_back/wx_back_08"},{"time":0.3,"name":"wx_back/wx_back_09"},{"time":0.3333,"name":"wx_back/wx_back_10"},{"time":0.3667,"name":"wx_back/wx_back_11"},{"time":0.4,"name":"wx_back/wx_back_12"},{"time":0.4333,"name":"wx_back/wx_back_13"},{"time":0.4667,"name":"wx_back/wx_back_14"},{"time":0.5,"name":"wx_back/wx_back_15"},{"time":0.5333,"name":"wx_back/wx_back_16"},{"time":0.5667,"name":"wx_back/wx_back_17"},{"time":0.6,"name":"wx_back/wx_back_18"},{"time":0.6333,"name":"wx_back/wx_back_19"},{"time":0.6667,"name":"wx_back/wx_back_20"},{"time":0.7,"name":"wx_back/wx_back_21"},{"time":0.7333,"name":"wx_back/wx_back_22"},{"time":0.7667,"name":"wx_back/wx_back_23"},{"time":0.8,"name":"wx_back/wx_back_24"},{"time":0.8333,"name":"wx_back/wx_back_25"},{"time":0.8667,"name":"wx_back/wx_back_26"},{"time":0.9,"name":"wx_back/wx_back_27"},{"time":0.9333,"name":"wx_back/wx_back_28"},{"time":0.9667,"name":"wx_back/wx_back_29"},{"time":1,"name":"wx_back/wx_back_00"}]},"wx_cloth":{"attachment":[{"name":"wx_cloth"}]},"wx_face":{"attachment":[{"name":"wx_face"}]},"wx_frame1":{"attachment":[{"name":"wx_frame1"}]},"wx_frame2":{"attachment":[{"name":"wx_frame2"}]},"wx_gun":{"attachment":[{"name":"wx_gun"}]},"wx_hair1":{"attachment":[{"name":"wx_hair1"}]},"wx_hair2":{"attachment":[{"name":"wx_hair2"}]},"wx_hair3":{"attachment":[{"name":"wx_hair3"}]},"wx_hat1":{"attachment":[{"name":"wx_hat1"}]},"wx_hat2":{"attachment":[{"name":"wx_hat2"}]},"wx_mask":{"attachment":[{"name":"wx_mask"}]},"wx_ms-MY":{"attachment":[{"name":"ms-MY"}]},"wx_ms-MY_add":{"color":[{"color":"ffffff00","curve":0.25,"c3":0.75},{"time":0.8333,"color":"ffffffff"}],"attachment":[{"name":"ms-MY"}]},"wx_spark":{"attachment":[{"time":0.1667,"name":"spark/spark_00"},{"time":0.2,"name":"spark/spark_01"},{"time":0.2333,"name":"spark/spark_02"},{"time":0.2667,"name":"spark/spark_03"},{"time":0.3,"name":"spark/spark_04"},{"time":0.3333,"name":"spark/spark_00"},{"time":0.3667,"name":"spark/spark_01"},{"time":0.4,"name":"spark/spark_02"},{"time":0.4333,"name":"spark/spark_03"},{"time":0.4667,"name":"spark/spark_04"},{"time":0.5,"name":"spark/spark_05"},{"time":0.5333,"name":"spark/spark_06"},{"time":0.5667,"name":"spark/spark_07"},{"time":0.6,"name":"spark/spark_08"},{"time":0.6333,"name":"spark/spark_09"},{"time":0.6667,"name":null}]}},"bones":{"wx":{"scale":[{"curve":0.25,"c3":0.75},{"time":0.1,"x":0.9,"y":0.9,"curve":0.25,"c3":0.75},{"time":0.2,"x":1.15,"y":1.15,"curve":0.25,"c3":0.75},{"time":0.6667,"x":1.2,"y":1.2,"curve":0.25,"c3":0.75},{"time":0.8,"x":0.9,"y":0.9,"curve":0.25,"c3":0.75},{"time":0.9333}]},"wx_word":{"scale":[{"curve":0.25,"c3":0.75},{"time":0.1667,"x":0.9,"y":0.9,"curve":0.25,"c3":0.75},{"time":0.2667,"x":1.15,"y":1.15,"curve":0.25,"c3":0.75},{"time":0.7333,"x":1.2,"y":1.2,"curve":0.25,"c3":0.75},{"time":0.8667,"x":0.9,"y":0.9,"curve":0.25,"c3":0.75},{"time":1}]},"wx_gun":{"rotate":[{"time":0.1333,"curve":0.25,"c3":0.75},{"time":0.2,"angle":4.68,"curve":0.25,"c3":0.75},{"time":0.2667,"angle":-21.44,"curve":0.25,"c3":0.75},{"time":0.3333,"angle":4.68,"curve":0.25,"c3":0.75},{"time":0.4,"angle":-21.44,"curve":0.25,"c3":0.75},{"time":0.4667}],"translate":[{"time":0.2,"curve":0.25,"c3":0.75},{"time":0.2667,"y":-9.34,"curve":0.25,"c3":0.75},{"time":0.3333,"curve":0.25,"c3":0.75},{"time":0.4,"y":-12.07,"curve":0.25,"c3":0.75},{"time":0.4667,"y":4.64,"curve":0.25,"c3":0.75},{"time":0.6667}],"scale":[{"time":0.1333,"curve":0.25,"c3":0.75},{"time":0.2667,"x":1.1,"y":1.1,"curve":"stepped"},{"time":0.8,"x":1.1,"y":1.1,"curve":0.25,"c3":0.75},{"time":1}]},"wx_hair1-1":{"rotate":[{"curve":0.25,"c3":0.75},{"time":0.3667,"angle":-4.77,"curve":0.25,"c3":0.75},{"time":1}]},"wx_hair2-1":{"rotate":[{"curve":0.25,"c3":0.75},{"time":0.5333,"angle":-4.94,"curve":0.25,"c3":0.75},{"time":1}]},"wx_hair3-1":{"rotate":[{"curve":0.25,"c3":0.75},{"time":0.4333,"angle":4.83,"curve":0.25,"c3":0.75},{"time":1}]},"wx_head":{"translate":[{"time":0.2333,"curve":0.25,"c3":0.75},{"time":0.3333,"y":-4.08,"curve":0.25,"c3":0.75},{"time":0.4333,"curve":0.25,"c3":0.75},{"time":0.5,"y":-4.08,"curve":0.25,"c3":0.75},{"time":0.5667,"y":4.64,"curve":0.25,"c3":0.75},{"time":0.7667}]},"wx_hair1-3":{"rotate":[{"curve":0.25,"c3":0.75},{"time":0.5,"angle":-5.86,"curve":0.25,"c3":0.75},{"time":1}]},"wx_hair1-2":{"rotate":[{"curve":0.25,"c3":0.75},{"time":0.4333,"angle":-5.22,"curve":0.25,"c3":0.75},{"time":1}]},"wx_hair2-2":{"rotate":[{"curve":0.25,"c3":0.75},{"time":0.6,"angle":-5.43,"curve":0.25,"c3":0.75},{"time":1}]},"wx_hair3-2":{"rotate":[{"curve":0.25,"c3":0.75},{"time":0.5,"angle":4.37,"curve":0.25,"c3":0.75},{"time":1}]},"wx_ani":{"translate":[{"y":-5.13}]},"wx_char":{"translate":[{"x":-6.28,"y":7.18}],"scale":[{"x":1.15,"y":1.15}]}},"deform":{"default":{"wx_face":{"wx_face":[{"curve":0.25,"c3":0.75},{"time":0.3333,"offset":48,"curve":"stepped","vertices":[0.27465,-0.01194,0.08509,-0.37561,0.07631,-0.71894,0.39173,-1.88672,1.07136,-1.75986,0.94069,-1.42856,0,0,-0.5533,0.01714,-0.36349,-0.02948,-1.10625,0.04193,-0.70261,-1.21543,0.20475,-1.91328,0.95144,-2.32029,1.21865,-2.24328,1.59333,-0.08265,1.5634,-0.09872,1.04972,-0.0805,0.1681,0.08599]},{"time":0.5667,"offset":48,"curve":0.25,"c3":0.75,"vertices":[0.27465,-0.01194,0.08509,-0.37561,0.07631,-0.71894,0.39173,-1.88672,1.07136,-1.75986,0.94069,-1.42856,0,0,-0.5533,0.01714,-0.36349,-0.02948,-1.10625,0.04193,-0.70261,-1.21543,0.20475,-1.91328,0.95144,-2.32029,1.21865,-2.24328,1.59333,-0.08265,1.5634,-0.09872,1.04972,-0.0805,0.1681,0.08599]},{"time":0.6667,"offset":30,"curve":0.25,"c3":0.75,"vertices":[-1.99896,0,-3.15126,-0.01202,-2.37257,0.29446,-0.95935,0.44958,0,0,0.2183,0.0177,1.67921,0.15812,1.98248,-0.2077,1.2185,-0.29929,0.27465,-0.01194,0.08509,-0.37561,0.07397,-0.15083,0.4915,-1.76933,0.78497,-1.19293,0.43715,-0.87924,0,0,-0.41948,-0.01572,-0.36349,-0.02948,-1.10625,0.04193,-0.43498,-1.28115,0.15428,-1.82994,0.49604,-1.2862,1.0649,-1.42516,1.04167,-0.01809,1.4296,-0.06584,1.04972,-0.0805,0.1681,0.08599]},{"time":0.7667,"offset":48,"vertices":[0.27465,-0.01194,0.08509,-0.37561,0.07631,-0.71894,0.39173,-1.88672,1.07136,-1.75986,0.94069,-1.42856,0,0,-0.5533,0.01714,-0.36349,-0.02948,-1.10625,0.04193,-0.70261,-1.21543,0.20475,-1.91328,0.95144,-2.32029,1.21865,-2.24328,1.59333,-0.08265,1.5634,-0.09872,1.04972,-0.0805,0.1681,0.08599]}]},"wx_mask":{"wx_mask":[{"offset":1,"vertices":[-74.98387,10.00999,0,0,0,78.76077,-16.5099,6.13199]}]}}}}}}